annotest/__init__.py
annotest/__main__.py
annotest/an_language.py
annotest/app.py
annotest/commandline.py
annotest/common.py
annotest/constant.py
annotest/file.py
annotest/version.py
annotest/preparation/__init__.py
annotest/preparation/fixer_step.py
annotest/preparation/trimmer.py
annotest/project_info/__init__.py
annotest/project_info/astlib.py
annotest/project_info/collecter.py
annotest/project_info/generator_linker.py
annotest/project_info/project_type.py
annotest/project_info/decorator_info/__init__.py
annotest/project_info/decorator_info/argument_type.py
annotest/project_info/decorator_info/astlib.py
annotest/project_info/decorator_info/decorator_type.py
annotest/unittest_engine/__init__.py
annotest/unittest_engine/astlib.py
annotest/unittest_engine/generator.py
annotest/unittest_engine/hypothesis_lib/__init__.py
annotest/unittest_engine/hypothesis_lib/decorator.py
tests/__init__.py
tests/test_project_info.py
annotest-0.1.1.dist-info/LICENSE
annotest-0.1.1.dist-info/METADATA
annotest-0.1.1.dist-info/WHEEL
annotest-0.1.1.dist-info/entry_points.txt
annotest-0.1.1.dist-info/top_level.txt
annotest-0.1.1.dist-info/RECORD
