Metadata-Version: 2.1
Name: aNNoTest
Version: 0.1.1
Summary: A tool to automatically generating bug-finding inputs for neural network program testing.
Home-page: https://github.com/atom-sw/annotest
Author: Mohammad Rezaalipour
Author-email: rezaalipour.mohammad@gmail.com
Requires-Python: >=3.6
License-File: LICENSE
Requires-Dist: astor~=0.8.1
Requires-Dist: autoflake~=1.4
Requires-Dist: hypothesis~=6.4
Requires-Dist: black
